xspeedhack/__init__.py
xspeedhack/client.py
xspeedhack/bin/injector32.exe
xspeedhack/bin/injector64.exe
xspeedhack/bin/speedhack32.dll
xspeedhack/bin/speedhack64.dll
xspeedhack-0.0.3.dist-info/LICENSE
xspeedhack-0.0.3.dist-info/METADATA
xspeedhack-0.0.3.dist-info/WHEEL
xspeedhack-0.0.3.dist-info/top_level.txt
xspeedhack-0.0.3.dist-info/RECORD
