Metadata-Version: 2.1
Name: xspeedhack
Version: 0.0.3
Summary: Universal speedhack library for Python
Author-email: Loïc Magne <loic.magne@outlook.com>
License: MIT License
Keywords: speedhack,games,speed,cheat
Classifier: Programming Language :: Python :: 3
Requires-Python: >=3.8
License-File: LICENSE
Requires-Dist: psutil>=6.0.0
Requires-Dist: pywin32>=306; platform_system == "Windows"
Provides-Extra: dev
Requires-Dist: pytest; extra == "dev"
Requires-Dist: ruff; extra == "dev"
